{
  "tasks": [
    {
      "id": "T1-001",
      "name": "Progressive Web App (PWA)",
      "tier": "KRITICKÁ VYLEPŠENÍ",
      "duration": "4 hours",
      "priority": 1,
      "complexity": "MEDIUM",
      "status": "pending"
    },
    {
      "id": "T1-002",
      "name": "Advanced Error Boundaries",
      "tier": "KRITICKÁ VYLEPŠENÍ",
      "duration": "3 hours",
      "priority": 2,
      "complexity": "MEDIUM",
      "status": "pending"
    },
    {
      "id": "T1-003",
      "name": "Performance Monitoring",
      "tier": "KRITICKÁ VYLEPŠENÍ",
      "duration": "6 hours",
      "priority": 3,
      "complexity": "HIGH",
      "status": "pending"
    },
    {
      "id": "T1-004",
      "name": "Accessibility (WCAG 2.1 AA)",
      "tier": "KRITICKÁ VYLEPŠENÍ",
      "duration": "5 hours",
      "priority": 4,
      "complexity": "MEDIUM",
      "status": "pending"
    },
    {
      "id": "T1-005",
      "name": "Security Hardening",
      "tier": "KRITICKÁ VYLEPŠENÍ",
      "duration": "4 hours",
      "priority": 5,
      "complexity": "MEDIUM",
      "status": "pending"
    },
    {
      "id": "T2-001",
      "name": "Undo/Redo System",
      "tier": "PRO FEATURES",
      "duration": "6 hours",
      "priority": 6,
      "complexity": "HIGH",
      "status": "pending"
    },
    {
      "id": "T2-002",
      "name": "Advanced Search & Filters",
      "tier": "PRO FEATURES",
      "duration": "5 hours",
      "priority": 7,
      "complexity": "MEDIUM",
      "status": "pending"
    },
    {
      "id": "T2-003",
      "name": "Drag & Drop Interface",
      "tier": "PRO FEATURES",
      "duration": "6 hours",
      "priority": 8,
      "complexity": "MEDIUM",
      "status": "pending"
    },
    {
      "id": "T2-004",
      "name": "Cloud Backup & Sync",
      "tier": "PRO FEATURES",
      "duration": "8 hours",
      "priority": 9,
      "complexity": "HIGH",
      "status": "pending"
    },
    {
      "id": "T2-005",
      "name": "Smart Auto-save",
      "tier": "PRO FEATURES",
      "duration": "4 hours",
      "priority": 10,
      "complexity": "MEDIUM",
      "status": "pending"
    },
    {
      "id": "T2-006",
      "name": "Data Validation Layer",
      "tier": "PRO FEATURES",
      "duration": "5 hours",
      "priority": 11,
      "complexity": "MEDIUM",
      "status": "pending"
    },
    {
      "id": "T3-001",
      "name": "Multi-Portfolio Management",
      "tier": "ENTERPRISE FEATURES",
      "duration": "10 hours",
      "priority": 12,
      "complexity": "HIGH",
      "status": "pending"
    },
    {
      "id": "T3-002",
      "name": "Advanced Analytics Dashboard",
      "tier": "ENTERPRISE FEATURES",
      "duration": "12 hours",
      "priority": 13,
      "complexity": "VERY HIGH",
      "status": "pending"
    },
    {
      "id": "T3-003",
      "name": "Benchmark Comparison",
      "tier": "ENTERPRISE FEATURES",
      "duration": "8 hours",
      "priority": 14,
      "complexity": "HIGH",
      "status": "pending"
    },
    {
      "id": "T3-004",
      "name": "Professional PDF Export",
      "tier": "ENTERPRISE FEATURES",
      "duration": "10 hours",
      "priority": 15,
      "complexity": "HIGH",
      "status": "pending"
    },
    {
      "id": "T3-005",
      "name": "Email Automation",
      "tier": "ENTERPRISE FEATURES",
      "duration": "8 hours",
      "priority": 16,
      "complexity": "HIGH",
      "status": "pending"
    },
    {
      "id": "T3-006",
      "name": "API Integration Layer",
      "tier": "ENTERPRISE FEATURES",
      "duration": "12 hours",
      "priority": 17,
      "complexity": "VERY HIGH",
      "status": "pending"
    },
    {
      "id": "T4-001",
      "name": "Advanced Theming System",
      "tier": "UX/UI ENHANCEMENTS",
      "duration": "6 hours",
      "priority": 18,
      "complexity": "MEDIUM",
      "status": "pending"
    },
    {
      "id": "T4-002",
      "name": "Animations & Micro-interactions",
      "tier": "UX/UI ENHANCEMENTS",
      "duration": "5 hours",
      "priority": 19,
      "complexity": "LOW",
      "status": "pending"
    },
    {
      "id": "T4-003",
      "name": "Responsive Design 2.0",
      "tier": "UX/UI ENHANCEMENTS",
      "duration": "8 hours",
      "priority": 20,
      "complexity": "MEDIUM",
      "status": "pending"
    },
    {
      "id": "T4-004",
      "name": "Guided Tours & Onboarding",
      "tier": "UX/UI ENHANCEMENTS",
      "duration": "6 hours",
      "priority": 21,
      "complexity": "MEDIUM",
      "status": "pending"
    },
    {
      "id": "T4-005",
      "name": "Customizable Dashboard",
      "tier": "UX/UI ENHANCEMENTS",
      "duration": "10 hours",
      "priority": 22,
      "complexity": "HIGH",
      "status": "pending"
    },
    {
      "id": "T5-001",
      "name": "Machine Learning Predictions",
      "tier": "ADVANCED FEATURES",
      "duration": "20 hours",
      "priority": 23,
      "complexity": "VERY HIGH",
      "status": "pending"
    },
    {
      "id": "T5-002",
      "name": "Real-time Market Data",
      "tier": "ADVANCED FEATURES",
      "duration": "12 hours",
      "priority": 24,
      "complexity": "HIGH",
      "status": "pending"
    },
    {
      "id": "T5-003",
      "name": "Collaboration Features",
      "tier": "ADVANCED FEATURES",
      "duration": "15 hours",
      "priority": 25,
      "complexity": "VERY HIGH",
      "status": "pending"
    },
    {
      "id": "T5-004",
      "name": "Mobile App (React Native)",
      "tier": "ADVANCED FEATURES",
      "duration": "40 hours",
      "priority": 26,
      "complexity": "VERY HIGH",
      "status": "pending"
    },
    {
      "id": "T5-005",
      "name": "Blockchain Integration",
      "tier": "ADVANCED FEATURES",
      "duration": "25 hours",
      "priority": 27,
      "complexity": "VERY HIGH",
      "status": "pending"
    }
  ],
  "metadata": {
    "total": 27,
    "completed": 0,
    "in_progress": 0,
    "pending": 27,
    "completion_percentage": 0.0,
    "timestamp": "2025-10-07T12:39:01.699406"
  }
}